symautomata
