Metadata-Version: 1.1
Name: symautomata
Version: 0.0.6
Summary: Automata classes
Home-page: https://github.com/GeorgeArgyros/symautomata
Author: George Argyros, Ioannis Stais
Author-email: ioannis.stais@gmail.com
License: UNKNOWN
Download-URL: https://github.com/GeorgeArgyros/symautomata/tarball/master
Platform: Any
Classifier: Development Status :: 3 - Alpha
Classifier: Programming Language :: Python
Classifier: Programming Language :: Python :: 2
Classifier: Programming Language :: Python :: 2.7
Classifier: Intended Audience :: Developers
Classifier: Environment :: Console
